<?xml version="1.0" encoding="utf-8" ?>
<PawnKindDefs>


  <PawnKindDef>
    <defName>MercenaryDriver</defName>
    <label>mercenary driver</label>
    <race>Human</race>
    <combatPower>70</combatPower>
    <defaultFactionType>Pirate</defaultFactionType>
    <baseRecruitDifficulty>80</baseRecruitDifficulty>
    <backstoryCategory>Raider</backstoryCategory>
    <invFoodCount>1</invFoodCount>
    <itemQuality>Normal</itemQuality>
    <backstoryCryptosleepCommonality>0.25</backstoryCryptosleepCommonality>
    <maxGenerationAge>58</maxGenerationAge>
    <gearHealthRange>
      <min>0.7</min>
      <max>2.3</max>
    </gearHealthRange>
    <apparelTags>
      <li>Outlander</li>
      <li>Military</li>
    </apparelTags>
    <apparelMoney>
      <min>1500</min>
      <max>2800</max>
    </apparelMoney>
    <apparelAllowHeadwearChance>0.5</apparelAllowHeadwearChance>
    <weaponMoney>
      <min>400</min>
      <max>700</max>
    </weaponMoney>
    <weaponTags>
      <li>Gun</li>
    </weaponTags>
    <techHediffsMoney>
      <min>1000</min>
      <max>1500</max>
    </techHediffsMoney>
    <techHediffsTags>
      <li>Advanced</li>
    </techHediffsTags>
    <techHediffsChance>0.003</techHediffsChance>
    <inventoryOptions>
      <skipChance>0.8</skipChance>
      <subOptionsChooseOne>
        <li>
          <thingDef>Silver</thingDef>
          <countRange>
            <min>50</min>
            <max>200</max>
          </countRange>
        </li>
        <li>
          <thingDef>Medicine</thingDef>
          <countRange>
            <min>1</min>
            <max>1</max>
          </countRange>
        </li>
      </subOptionsChooseOne>
    </inventoryOptions>
  </PawnKindDef>




</PawnKindDefs>